LICENSE
README.md
pyproject.toml
setup.py
minesweeper/__init__.py
minesweeper/__main__.py
minesweeper/board.py
minesweeper/box.py
minesweeper/config.py
minesweeper/debug.py
minesweeper/main.py
minesweeper/ui.py
terminal_minesweeper.egg-info/PKG-INFO
terminal_minesweeper.egg-info/SOURCES.txt
terminal_minesweeper.egg-info/dependency_links.txt
terminal_minesweeper.egg-info/entry_points.txt
terminal_minesweeper.egg-info/requires.txt
terminal_minesweeper.egg-info/top_level.txt